payman_zibal-1.0.3.dist-info/licenses/LICENSE
zibal/__init__.py
zibal/gateway.py
zibal/adapters/__init__.py
zibal/adapters/error_mapper.py
zibal/adapters/http_client.py
zibal/enums/__init__.py
zibal/enums/result_code.py
zibal/enums/transaction_status.py
zibal/exceptions/__init__.py
zibal/exceptions/zibal_exceptions.py
zibal/methods/__init__.py
zibal/methods/callback.py
zibal/methods/lazy_payment.py
zibal/methods/payment_initiator.py
zibal/methods/payment_inquiry.py
zibal/methods/redirector.py
zibal/methods/verify_payment.py
zibal/models/__init__.py
zibal/models/callback.py
zibal/models/inquiry_request.py
zibal/models/inquiry_response.py
zibal/models/lazy_callback.py
zibal/models/multiplexing_info.py
zibal/models/payment_request.py
zibal/models/payment_response.py
zibal/models/types.py
zibal/models/verify_request.py
zibal/models/verify_response.py
payman_zibal-1.0.3.dist-info/METADATA
payman_zibal-1.0.3.dist-info/WHEEL
payman_zibal-1.0.3.dist-info/top_level.txt
payman_zibal-1.0.3.dist-info/RECORD
